aioasyncsqlite/__init__.py
aioasyncsqlite/__version__.py
aioasyncsqlite/context.py
aioasyncsqlite/core.py
aioasyncsqlite/cursor.py
aioasyncsqlite/py.typed
aioasyncsqlite-1.0.0.dist-info/licenses/LICENSE
aioasyncsqlite-1.0.0.dist-info/WHEEL
aioasyncsqlite-1.0.0.dist-info/METADATA
aioasyncsqlite-1.0.0.dist-info/RECORD
