Metadata-Version: 2.4
Name: aioasyncsqlite
Version: 1.0.0
Summary: asyncio bridge to the standard sqlite3 module
Author: xacepok933
Requires-Python: >=3.9
Classifier: Development Status :: 5 - Production/Stable
Classifier: Framework :: AsyncIO
Classifier: Intended Audience :: Developers
Classifier: License :: OSI Approved :: MIT License
Classifier: Topic :: Software Development :: Libraries
License-File: LICENSE
Requires-Dist: typing_extensions >= 4.0
Requires-Dist: attribution==1.7.1 ; extra == "dev"
Requires-Dist: black==24.3.0 ; extra == "dev"
Requires-Dist: build>=1.2 ; extra == "dev"
Requires-Dist: coverage[toml]==7.6.10 ; extra == "dev"
Requires-Dist: flake8==7.0.0 ; extra == "dev"
Requires-Dist: flake8-bugbear==24.12.12 ; extra == "dev"
Requires-Dist: flit==3.10.1 ; extra == "dev"
Requires-Dist: mypy==1.14.1 ; extra == "dev"
Requires-Dist: ufmt==2.5.1 ; extra == "dev"
Requires-Dist: usort==1.0.8.post1 ; extra == "dev"
Requires-Dist: sphinx==8.1.3 ; extra == "docs"
Requires-Dist: sphinx-mdinclude==0.6.1 ; extra == "docs"
Provides-Extra: dev
Provides-Extra: docs
